Topsis_Ananya_102016083/__init__.py
Topsis_Ananya_102016083/topsis.py
Topsis_Ananya_102016083-1.1.0.dist-info/LICENSE.txt
Topsis_Ananya_102016083-1.1.0.dist-info/METADATA
Topsis_Ananya_102016083-1.1.0.dist-info/WHEEL
Topsis_Ananya_102016083-1.1.0.dist-info/top_level.txt
Topsis_Ananya_102016083-1.1.0.dist-info/RECORD
